ong_utils/__init__.py
ong_utils/async_utils.py
ong_utils/config.py
ong_utils/credentials.py
ong_utils/desktop_shortcut.py
ong_utils/excel.py
ong_utils/import_utils.py
ong_utils/internal_storage.py
ong_utils/jwt_tokens.py
ong_utils/parse_html.py
ong_utils/selenium_chrome.py
ong_utils/sensitivity_labels.py
ong_utils/timers.py
ong_utils/ui.py
ong_utils/ui_logging_utils.py
ong_utils/urllib3_utils.py
ong_utils/utils.py
ong_utils/web.py
ong_utils/config_utils/__init__.py
ong_utils/config_utils/config_utils.py
ong_utils/office/__init__.py
ong_utils/office/office_base.py
ong_utils-1.0.6.dist-info/licenses/LICENSE.txt
ong_utils-1.0.6.dist-info/METADATA
ong_utils-1.0.6.dist-info/WHEEL
ong_utils-1.0.6.dist-info/top_level.txt
ong_utils-1.0.6.dist-info/RECORD
