Metadata-Version: 2.4
Name: ong_utils
Version: 1.0.6
Summary: Common utilities for python projects
Author-email: Oscar Neira <oneirag@yahoo.es>
Project-URL: Homepage, https://github.com/Oneirag/ong_utils
Project-URL: Source, https://github.com/Oneirag/ong_utils
Classifier: Programming Language :: Python
Classifier: License :: OSI Approved :: MIT License
Requires-Python: >=3.8
License-File: LICENSE.txt
Requires-Dist: certifi
Requires-Dist: urllib3
Requires-Dist: pyopenssl
Requires-Dist: python-dateutil
Requires-Dist: pyyaml
Requires-Dist: ujson
Requires-Dist: idna
Requires-Dist: keyring
Requires-Dist: nest-asyncio
Provides-Extra: jwt
Requires-Dist: pyjwt; extra == "jwt"
Provides-Extra: shortcuts
Requires-Dist: pyshortcuts; extra == "shortcuts"
Requires-Dist: Pillow; sys_platform != "darwin" and extra == "shortcuts"
Requires-Dist: icnsutil; sys_platform == "darwin" and extra == "shortcuts"
Requires-Dist: wheel; extra == "shortcuts"
Provides-Extra: xlsx
Requires-Dist: openpyxl; extra == "xlsx"
Requires-Dist: pandas; extra == "xlsx"
Provides-Extra: selenium
Requires-Dist: selenium; extra == "selenium"
Requires-Dist: selenium-wire; extra == "selenium"
Requires-Dist: undetected-chromedriver; extra == "selenium"
Provides-Extra: credentials
Requires-Dist: pywin32; platform_system == "Windows" and extra == "credentials"
Requires-Dist: python-pam; platform_system != "Windows" and extra == "credentials"
Provides-Extra: office
Requires-Dist: pywin32; extra == "office"
Provides-Extra: all
Requires-Dist: pywin32; platform_system == "Windows" and extra == "all"
Requires-Dist: python-pam; platform_system != "Windows" and extra == "all"
Requires-Dist: selenium; extra == "all"
Requires-Dist: selenium-wire; extra == "all"
Requires-Dist: undetected-chromedriver; extra == "all"
Requires-Dist: openpyxl; extra == "all"
Requires-Dist: pandas; extra == "all"
Requires-Dist: pyshortcuts; extra == "all"
Requires-Dist: Pillow; sys_platform != "darwin" and extra == "all"
Requires-Dist: icnsutil; sys_platform == "darwin" and extra == "all"
Requires-Dist: wheel; extra == "all"
Requires-Dist: pyjwt; extra == "all"
Requires-Dist: pywin32; extra == "all"
Dynamic: license-file
